{
	"name": "AzureSql",
	"properties": {
		"activities": [
			{
				"name": "copy data from azure sql",
				"type": "Copy",
				"dependsOn": [
					{
						"activity": "lastLoad",
						"dependencyConditions": [
							"Succeeded"
						]
					},
					{
						"activity": "latestload",
						"dependencyConditions": [
							"Succeeded"
						]
					}
				],
				"policy": {
					"timeout": "0.12:00:00",
					"retry": 0,
					"retryIntervalInSeconds": 30,
					"secureOutput": false,
					"secureInput": false
				},
				"userProperties": [],
				"typeProperties": {
					"source": {
						"type": "AzureSqlSource",
						"sqlReaderQuery": {
							"value": "select * from FactBookings where booking_date\n> '@{activity('lastLoad').output.firstRow.lastload}'",
							"type": "Expression"
						},
						"queryTimeout": "02:00:00",
						"partitionOption": "None"
					},
					"sink": {
						"type": "DelimitedTextSink",
						"storeSettings": {
							"type": "AzureBlobFSWriteSettings"
						},
						"formatSettings": {
							"type": "DelimitedTextWriteSettings",
							"quoteAllText": true,
							"fileExtension": ".txt"
						}
					},
					"enableStaging": false,
					"translator": {
						"type": "TabularTranslator",
						"typeConversion": true,
						"typeConversionSettings": {
							"allowDataTruncation": true,
							"treatBooleanAsNumber": false
						}
					}
				},
				"inputs": [
					{
						"referenceName": "AzureSqlTable",
						"type": "DatasetReference"
					}
				],
				"outputs": [
					{
						"referenceName": "sinkIncrementalData",
						"type": "DatasetReference"
					}
				]
			},
			{
				"name": "lastLoad",
				"description": "we are just getting the value from last load json file to get a checkpoint.",
				"type": "Lookup",
				"dependsOn": [],
				"policy": {
					"timeout": "0.12:00:00",
					"retry": 0,
					"retryIntervalInSeconds": 30,
					"secureOutput": false,
					"secureInput": false
				},
				"userProperties": [],
				"typeProperties": {
					"source": {
						"type": "JsonSource",
						"storeSettings": {
							"type": "AzureBlobFSReadSettings",
							"recursive": true,
							"enablePartitionDiscovery": false
						},
						"formatSettings": {
							"type": "JsonReadSettings"
						}
					},
					"dataset": {
						"referenceName": "lastLoad",
						"type": "DatasetReference"
					}
				}
			},
			{
				"name": "latestload",
				"description": "we will get the checkpoint(max value by date) from the azure table.",
				"type": "Lookup",
				"dependsOn": [],
				"policy": {
					"timeout": "0.12:00:00",
					"retry": 0,
					"retryIntervalInSeconds": 30,
					"secureOutput": false,
					"secureInput": false
				},
				"userProperties": [],
				"typeProperties": {
					"source": {
						"type": "AzureSqlSource",
						"sqlReaderQuery": "select max(booking_date) as latestload from FactBookings",
						"queryTimeout": "02:00:00",
						"partitionOption": "None"
					},
					"dataset": {
						"referenceName": "AzureSqlTable",
						"type": "DatasetReference"
					}
				}
			},
			{
				"name": "Watermark change lastload with latestload",
				"type": "Copy",
				"dependsOn": [
					{
						"activity": "copy data from azure sql",
						"dependencyConditions": [
							"Succeeded"
						]
					}
				],
				"policy": {
					"timeout": "0.12:00:00",
					"retry": 0,
					"retryIntervalInSeconds": 30,
					"secureOutput": false,
					"secureInput": false
				},
				"userProperties": [],
				"typeProperties": {
					"source": {
						"type": "JsonSource",
						"additionalColumns": [
							{
								"name": "lastload",
								"value": {
									"value": "@activity('latestload').output.firstRow.latestload",
									"type": "Expression"
								}
							}
						],
						"storeSettings": {
							"type": "AzureBlobFSReadSettings",
							"recursive": true,
							"enablePartitionDiscovery": false
						},
						"formatSettings": {
							"type": "JsonReadSettings"
						}
					},
					"sink": {
						"type": "JsonSink",
						"storeSettings": {
							"type": "AzureBlobFSWriteSettings"
						},
						"formatSettings": {
							"type": "JsonWriteSettings"
						}
					},
					"enableStaging": false
				},
				"inputs": [
					{
						"referenceName": "emptyJson",
						"type": "DatasetReference"
					}
				],
				"outputs": [
					{
						"referenceName": "lastLoad",
						"type": "DatasetReference"
					}
				]
			}
		],
		"annotations": [],
		"lastPublishTime": "2025-09-27T13:13:09Z"
	},
	"type": "Microsoft.DataFactory/factories/pipelines"
}